django_aieditor/__init__.py
django_aieditor/apps.py
django_aieditor/fields.py
django_aieditor/urls.py
django_aieditor/views.py
django_aieditor/static/django_aieditor/css/aieditor.min.css
django_aieditor/static/django_aieditor/css/style.css
django_aieditor/static/django_aieditor/js/aieditor.umd.js
django_aieditor/static/django_aieditor/js/index.js
django_aieditor/static/django_aieditor/js/init.js
django_aieditor/templates/django_aieditor/widget.html
django_aieditor-1.0.14.dist-info/licenses/LICENSE
django_aieditor-1.0.14.dist-info/METADATA
django_aieditor-1.0.14.dist-info/WHEEL
django_aieditor-1.0.14.dist-info/top_level.txt
django_aieditor-1.0.14.dist-info/RECORD
